{"2022-1":[{"title":"First Blog","date":"2022-01-01T08:24:33.000Z","link":"/2022/01/01/First Blog/"},{"title":"SQL注入","date":"2022-01-16T12:32:30.000Z","link":"/2022/01/16/SQL注入/"},{"title":"逻辑越权","date":"2022-01-16T13:32:30.000Z","link":"/2022/01/16/逻辑越权/"},{"title":"XSS跨站脚本攻击","date":"2022-01-17T14:56:33.000Z","link":"/2022/01/17/XSS跨站脚本攻击/"},{"title":"安全小白怎么从零开始拥有自己的武器库","date":"2022-01-20T08:47:24.000Z","link":"/2022/01/20/安全小白怎么从零开始拥有自己的武器库/"}],"2022-2":[{"title":"外网渗透信息收集","date":"2022-02-10T01:20:39.000Z","link":"/2022/02/10/外网渗透信息收集/"},{"title":"关于开深信服VPN无法抓包","date":"2022-02-17T02:12:50.000Z","link":"/2022/02/17/关于开深信服VPN无法抓包/"}],"2022-3":[{"title":"Air Cargo Management System v1.0存在SQL注入漏洞","date":"2022-03-08T01:13:19.000Z","link":"/2022/03/08/Air-Cargo-Management-System-v1-0存在SQL注入漏洞/"},{"title":"College Website Content Management System v1.0存在任意文件删除漏洞","date":"2022-03-08T01:13:19.000Z","link":"/2022/03/08/College-Website-Content-Management-System-v1-0存在任意文件删除漏洞/"},{"title":"TaoCMS存在代码执行漏洞","date":"2022-03-08T01:13:19.000Z","link":"/2022/03/08/TaoCMS存在代码执行漏洞/"},{"title":"文件上传漏洞个人总结","date":"2022-03-08T09:24:44.000Z","link":"/2022/03/08/文件上传个人总结/"},{"title":"文件包含漏洞个人总结","date":"2022-03-08T12:16:56.000Z","link":"/2022/03/08/文件包含漏洞个人总结/"},{"title":"文件下载漏洞个人总结","date":"2022-03-08T12:25:02.000Z","link":"/2022/03/08/文件下载漏洞个人总结/"},{"title":"CSRF 跨站请求伪造漏洞","date":"2022-03-08T12:28:25.000Z","link":"/2022/03/08/CSRF-跨站请求伪造漏洞/"},{"title":"SSRF服务器端请求伪造","date":"2022-03-08T12:30:40.000Z","link":"/2022/03/08/SSRF服务器端请求伪造/"},{"title":"RCE漏洞","date":"2022-03-08T12:33:37.000Z","link":"/2022/03/08/RCE漏洞/"},{"title":"常规绕WAF思路","date":"2022-03-08T12:44:54.000Z","link":"/2022/03/08/常规绕WAF思路/"},{"title":"常见端口攻击方式","date":"2022-03-08T12:45:37.000Z","link":"/2022/03/08/常见端口攻击方式/"},{"title":"排序算法","date":"2022-03-25T02:47:10.000Z","link":"/2022/03/25/排序算法/"}],"2022-4":[{"title":"记一次windows应急响应","date":"2022-04-23T18:11:30.000Z","link":"/2022/04/24/记一次windows应急响应/"}],"2022-5":[{"title":"word文档批量处理脚本","date":"2022-05-13T07:09:24.000Z","link":"/2022/05/13/word文档批量处理脚本/"},{"title":"反弹shell合集","date":"2022-05-13T08:25:02.000Z","link":"/2022/05/13/反弹shell合集/"},{"title":"不出网主机的几种上线方式","date":"2022-05-31T07:22:01.000Z","link":"/2022/05/31/不出网主机的几种上线方式/"}],"2022-7":[{"title":"近源攻击方式总结","date":"2022-07-19T08:40:21.000Z","link":"/2022/07/19/近源攻击方式总结/"}],"2022-8":[{"title":"微信小程序反编译-模拟器版","date":"2022-08-29T06:31:30.000Z","link":"/2022/08/29/微信小程序反编译-模拟器版/"},{"title":"微信小程序反编译-PC微信版","date":"2022-08-29T06:39:44.000Z","link":"/2022/08/29/微信小程序反编译-PC微信版/"}],"2022-9":[{"title":"六种常见的网络钓鱼攻击以及如何防范它们","date":"2022-09-17T02:00:53.000Z","link":"/2022/09/17/六种常见的网络钓鱼攻击以及如何防范它们/"}],"2022-10":[{"title":"钓鱼场景下微信聊天记录回传","date":"2022-10-27T02:55:32.000Z","link":"/2022/10/27/钓鱼场景下微信聊天记录回传/"}],"2023-4":[{"title":"PowerShell Community","date":"2023-04-17T01:45:01.000Z","link":"/2023/04/17/PowerShell-Community/"},{"title":"钓鱼平台搭建","date":"2023-04-17T07:47:57.000Z","link":"/2023/04/17/钓鱼平台搭建/"},{"title":"Windows权限维持总结","date":"2023-04-18T16:08:48.000Z","link":"/2023/04/19/Windows权限维持总结/"},{"title":"委派攻击","date":"2023-04-19T13:05:14.000Z","link":"/2023/04/19/委派攻击/"},{"title":"如何在不进行审计的情况下对小程序加密数据进行解密","date":"2023-04-21T09:21:26.000Z","link":"/2023/04/21/如何在不进行审计的情况下对小程序加密数据进行解密/"},{"title":"邮件服务器搭建","date":"2023-04-21T15:04:22.000Z","link":"/2023/04/21/邮件服务器搭建/"},{"title":"gophish搭建&使用","date":"2023-04-21T15:06:23.000Z","link":"/2023/04/21/gophish搭建-使用/"},{"title":"安全开发之Ax_url_interface","date":"2023-04-23T08:44:14.000Z","link":"/2023/04/23/安全开发之Ax-url-interface/"}]}